ell/__init__.py
ell/limbdark.py
ell/orbit.py
ell/surface.py
olio/__init__.py
olio/limbdark.py
olio/orbit.py
olio/surface.py
olio-0.0.1.dist-info/LICENSE
olio-0.0.1.dist-info/METADATA
olio-0.0.1.dist-info/WHEEL
olio-0.0.1.dist-info/top_level.txt
olio-0.0.1.dist-info/RECORD
