Metadata-Version: 2.1
Name: olio
Version: 0.0.1
Summary: Utilities and models for Rossiter-McLaughlin analyses.
Home-page: https://github.com/vedad/olio
Author: Vedad Kunovac
Author-email: vxh710@bham.ac.uk
License: UNKNOWN
Platform: UNKNOWN
Classifier: Programming Language :: Python :: 3
Classifier: License :: OSI Approved :: MIT License
Classifier: Operating System :: OS Independent
Requires-Python: >=3.6
